controlador_cache/src/mock_memory.sv
`timescale 1ns / 1ps
import cache_pkg::*;

module mock_memory (
    input  logic                                clk,
    input  logic                                rst_n,

    // Sinais conectados ao controlador de cache
    input  logic                                mem_req_i,
    input  logic [ADDR_WIDTH-1:0]               mem_addr_i,
    input  logic                                mem_write_i,
    input  logic [(DATA_WIDTH*BLOCK_SIZE)-1:0]  mem_wdata_i,

    output logic [(DATA_WIDTH*BLOCK_SIZE)-1:0]  mem_rdata_o,
    output logic                                mem_ready_o
);
    // RAM: 256 blocos de 128 bits (4096 bytes). 
    // É pequena de propósito para simular rápido e não travar o PC,
    // mas grande o suficiente para testar a cache inteira (64 linhas).
    // ~dom
    logic [(DATA_WIDTH*BLOCK_SIZE)-1:0] ram [0:255];

    // O endereço de bloco ignora os 4 bits de offset de byte (pois o bloco tem 16 bytes)
    logic [7:0] block_addr;
    assign block_addr = mem_addr_i[11:4];

    // Variável para criar um atraso "falso" e simular a latência da memória
    logic [2:0] delay_counter;

    always_ff @(posedge clk or negedge rst_n) begin
        if (!rst_n) begin
            mem_ready_o   <= 1'b0;
            mem_rdata_o   <= '0;
            delay_counter <= '0;

            // Inicializa a RAM com valores sequenciais para facilitar o debug visual no GTKWave
            for (int i = 0; i < 256; i++) begin
                // Cada palavra do bloco recebe um valor único
                ram[i] <= {32'h00000003 + (i*16), 32'h00000002 + (i*16), 32'h00000001 + (i*16), 32'h00000000 + (i*16)};
            end
        end else begin
            // Valor padrão para não gerar latch
            mem_ready_o <= 1'b0;

            if (mem_req_i && !mem_ready_o) begin
                if (delay_counter < 3) begin
                    // Conta 3 ciclos de clock de "espera"
                    delay_counter <= delay_counter + 1;
                end else begin
                    // Terminou o atraso, a memória responde
                    mem_ready_o   <= 1'b1;
                    delay_counter <= '0; // Reseta para o próximo acesso

                    if (mem_write_i) begin
                        // LÓGICA DE ESCRITA:
                        // Como a CPU escreve palavras de 32 bits, mas o barramento tem 128 bits,
                        // usamos os bits [3:2] do endereço para saber qual parte do bloco atualizar,
                        // evitando destruir o resto do bloco que já estava na memória.
                        logic [1:0] w_offset = mem_addr_i[3:2];

                        if (w_offset == 2'b00) ram[block_addr][31:0]   <= mem_wdata_i[31:0];
                        if (w_offset == 2'b01) ram[block_addr][63:32]  <= mem_wdata_i[63:32];
                        if (w_offset == 2'b10) ram[block_addr][95:64]  <= mem_wdata_i[95:64];
                        if (w_offset == 2'b11) ram[block_addr][127:96] <= mem_wdata_i[127:96];
                    end else begin
                        // LÓGICA DE LEITURA:
                        // Entrega o bloco de 128 bits inteiro para a cache
                        mem_rdata_o <= ram[block_addr];
                    end
                end
            end else begin
                // Se a requisição cair, zera o contador
                delay_counter <= '0;
            end
        end
    end

endmodule : mock_memory

controlador_cache/src/data_array.sv
`timescale 1ns / 1ps
import cache_pkg::*;

module data_array (
    input  logic                                clk,
    input  logic                                we_i,           // Gravação ativa
    input  logic [1:0]                          word_en_i,      // 00 = Bloco todo, outros = palavra específica
    input  logic [INDEX_BITS-1:0]               index_i,        // Linha mapeada da cache
    input  logic [(DATA_WIDTH*BLOCK_SIZE)-1:0]   data_i,         // Entrada de dados (128 bits)
    output logic [(DATA_WIDTH*BLOCK_SIZE)-1:0]   data_o          // Saída de dados (128 bits)
);

    // Banco de memória interna: 64 linhas contendo 128 bits cada (4 palavras de 32 bits)
    logic [31:0] data_mem [0:CACHE_LINES-1][0:BLOCK_SIZE-1];

    // Lógica de Leitura Combinacional (Assíncrona)
    assign data_o = {data_mem[index_i][3], data_mem[index_i][2], data_mem[index_i][1], data_mem[index_i][0]};

    // Lógica de Escrita Síncrona
    always_ff @(posedge clk) begin
        if (we_i) begin
            if (word_en_i == 2'b00) begin
                // Gravação paralela de todas as 4 palavras (vinda da memória principal)
                data_mem[index_i][0] <= data_i[31:0];
                data_mem[index_i][1] <= data_i[63:32];
                data_mem[index_i][2] <= data_i[95:64];
                data_mem[index_i][3] <= data_i[127:96];
            end else begin
                // Gravação pontual de apenas uma palavra (vinda de um Hit de escrita da CPU)
                data_mem[index_i][word_en_i] <= data_i[31:0];
            end
        end
    end

endmodule : data_array

src/tag_array.sv
`timescale 1ns / 1ps
import cache_pkg::*;

module tag_array (
    input  logic                    clk,
    input  logic                    rst_n,
    
    input  logic                    we_i,       // Write Enable
    input  logic [INDEX_BITS-1:0]   index_i,    // Índice da linha
    input  logic [TAG_BITS-1:0]     tag_i,      // Tag a ser gravada
    
    output logic [TAG_BITS-1:0]     tag_o,      // Tag lida
    output logic                    valid_o     // Bit de validade
);

    // Substituindo a struct por dois arrays independentes para contornar o bug do iverilog
    logic [TAG_BITS-1:0] tag_mem   [0:CACHE_LINES-1];
    logic                valid_mem [0:CACHE_LINES-1];

    // Lógica de Leitura (Assíncrona)
    assign tag_o   = tag_mem[index_i];
    assign valid_o = valid_mem[index_i];

    // Variável para o laço de repetição declarada fora para evitar warning de lifetime
    integer i;

    // Lógica de Escrita e Reset (Síncrona)
    always_ff @(posedge clk or negedge rst_n) begin
        if (!rst_n) begin
            // Invalida toda a cache no reset
            for (i = 0; i < CACHE_LINES; i = i + 1) begin
                valid_mem[i] <= 1'b0;
                tag_mem[i]   <= '0;
            end
        end else if (we_i) begin
            // Grava a nova tag e marca como válida
            valid_mem[index_i] <= 1'b1;
            tag_mem[index_i]   <= tag_i;
        end
    end

endmodule : tag_array

src/cache_controller.sv
`timescale 1ns / 1ps
import cache_pkg::*;

module cache_controller (
    input  logic                    clk,
    input  logic                    rst_n,

    // Interface com a CPU
    input  logic                    cpu_req_i,
    input  logic [ADDR_WIDTH-1:0]   cpu_addr_i,
    input  logic                    cpu_write_i,
    input  logic [DATA_WIDTH-1:0]   cpu_wdata_i,
    output logic [DATA_WIDTH-1:0]   cpu_rdata_o,
    output logic                    cpu_ready_o,

    // Interface com a Memória Principal
    output logic                    mem_req_o,
    output logic [ADDR_WIDTH-1:0]   mem_addr_o,
    output logic                    mem_write_o,
    output logic [(DATA_WIDTH*BLOCK_SIZE)-1:0] mem_wdata_o,
    input  logic [(DATA_WIDTH*BLOCK_SIZE)-1:0] mem_rdata_i,
    input  logic                    mem_ready_i
);

    logic [TAG_BITS-1:0]   cpu_tag;
    logic [INDEX_BITS-1:0] cpu_index;
    logic [1:0]            word_offset;

    assign cpu_tag     = cpu_addr_i[ADDR_WIDTH-1 : ADDR_WIDTH-TAG_BITS];
    assign cpu_index   = cpu_addr_i[OFFSET_BITS+INDEX_BITS-1 : OFFSET_BITS];
    assign word_offset = cpu_addr_i[3:2];

    cache_state_e current_state, next_state;

    logic                    tag_we;
    logic [TAG_BITS-1:0]     tag_from_cache;
    logic                    valid_from_cache;

    logic                    data_we;
    logic [1:0]              data_word_mask;
    logic [(DATA_WIDTH*BLOCK_SIZE)-1:0] data_from_cache;
    logic [(DATA_WIDTH*BLOCK_SIZE)-1:0] data_to_cache;

    logic cache_hit;
    assign cache_hit = valid_from_cache && (tag_from_cache == cpu_tag);

    assign cpu_rdata_o = (word_offset == 2'b00) ? data_from_cache[31:0]   :
                         (word_offset == 2'b01) ? data_from_cache[63:32]  :
                         (word_offset == 2'b10) ? data_from_cache[95:64]  :
                                                  data_from_cache[127:96];

    tag_array u_tag_array (
        .clk     (clk),
        .rst_n   (rst_n),
        .we_i    (tag_we),
        .index_i (cpu_index),
        .tag_i   (cpu_tag),
        .tag_o   (tag_from_cache),
        .valid_o (valid_from_cache)
    );

    data_array u_data_array (
        .clk       (clk),
        .we_i      (data_we),
        .word_en_i (data_word_mask),
        .index_i   (cpu_index),
        .data_i    (data_to_cache),
        .data_o    (data_from_cache)
    );

    always_ff @(posedge clk or negedge rst_n) begin
        if (!rst_n) begin
            current_state <= IDLE;
        end else begin
            current_state <= next_state;
        end
    end

    // Usando always @(*) para evitar o bug de constant selects do iverilog antigo
    always @(*) begin
        next_state     = current_state;
        cpu_ready_o    = 1'b0;
        mem_req_o      = 1'b0;
        mem_write_o    = 1'b0;
        mem_addr_o     = cpu_addr_i;
        mem_wdata_o    = '0;

        tag_we         = 1'b0;
        data_we        = 1'b0;
        data_word_mask = 2'b00; 
        data_to_cache  = '0;

        case (current_state)
            
            IDLE: begin
                if (cpu_req_i) begin
                    next_state = COMPARE_TAG;
                end
            end

            COMPARE_TAG: begin
                if (cache_hit) begin 
                    if (cpu_write_i) begin 
                        data_we        = 1'b1;
                        data_word_mask = word_offset; 
                        data_to_cache  = {4{cpu_wdata_i}}; 
                        
                        mem_req_o   = 1'b1;
                        mem_write_o = 1'b1;
                        mem_addr_o  = cpu_addr_i;
                        mem_wdata_o = (word_offset == 2'b00) ? {96'b0, cpu_wdata_i} :
                                      (word_offset == 2'b01) ? {64'b0, cpu_wdata_i, 32'b0} :
                                      (word_offset == 2'b10) ? {32'b0, cpu_wdata_i, 64'b0} :
                                                               {cpu_wdata_i, 96'b0};
                        
                        if (mem_ready_i) begin
                            cpu_ready_o = 1'b1;
                            next_state  = IDLE;
                        end
                    end else begin
                        cpu_ready_o = 1'b1;
                        next_state  = IDLE;
                    end
                end 
                else begin
                    if (cpu_write_i) begin 
                        mem_req_o   = 1'b1;
                        mem_write_o = 1'b1;
                        mem_addr_o  = cpu_addr_i;
                        mem_wdata_o = {4{cpu_wdata_i}};
                        
                        if (mem_ready_i) begin
                            cpu_ready_o = 1'b1;
                            next_state  = IDLE;
                        end
                    end else begin
                        next_state = ALLOCATE;
                    end
                end
            end
            
            ALLOCATE: begin 
                mem_req_o   = 1'b1;
                mem_write_o = 1'b0;
                
                // Mascara matemática (zera os ultimos 4 bits) para alinhar ao bloco
                // Isso evita o erro de sintaxe com fatiamento de bits no simulador
                mem_addr_o  = cpu_addr_i & 32'hFFFFFFF0;
                
                if (mem_ready_i) begin
                    data_we        = 1'b1;
                    data_word_mask = 2'b00; 
                    data_to_cache  = mem_rdata_i;
                    
                    tag_we         = 1'b1;
                    next_state     = RECOVER;
                end
            end

            RECOVER: begin
                next_state = COMPARE_TAG;
            end

            default: next_state = IDLE;
        endcase
    end

endmodule : cache_controller

controlador_cache/src/tb_cache.sv
`timescale 1ns / 1ps
import cache_pkg::*;

module tb_cache;

    // sinais de clock e reset
    logic clk;
    logic rst_n;

    // sinais CPU <-> cache
    logic                    cpu_req;
    logic [ADDR_WIDTH-1:0]   cpu_addr;
    logic                    cpu_write;
    logic [DATA_WIDTH-1:0]   cpu_wdata;
    logic [DATA_WIDTH-1:0]   cpu_rdata;
    logic                    cpu_ready;

    // sinais cache <-> memoria principal
    logic                    mem_req;
    logic [ADDR_WIDTH-1:0]   mem_addr;
    logic                    mem_write;
    logic [(DATA_WIDTH*BLOCK_SIZE)-1:0] mem_wdata;
    logic [(DATA_WIDTH*BLOCK_SIZE)-1:0] mem_rdata;
    logic                    mem_ready;

    // 1 instanciação da cache
    cache_controller u_cache (
        .clk         (clk),
        .rst_n       (rst_n),
        .cpu_req_i   (cpu_req),
        .cpu_addr_i  (cpu_addr),
        .cpu_write_i (cpu_write),
        .cpu_wdata_i (cpu_wdata),
        .cpu_rdata_o (cpu_rdata),
        .cpu_ready_o (cpu_ready),
        .mem_req_o   (mem_req),
        .mem_addr_o  (mem_addr),
        .mem_write_o (mem_write),
        .mem_wdata_o (mem_wdata),
        .mem_rdata_i (mem_rdata),
        .mem_ready_i (mem_ready)
    );

    // 2 instanciação da memoria principal (mock)
    mock_memory u_mem (
        .clk         (clk),
        .rst_n       (rst_n),
        .mem_req_i   (mem_req),
        .mem_addr_i  (mem_addr),
        .mem_write_i (mem_write),
        .mem_wdata_i (mem_wdata),
        .mem_rdata_o (mem_rdata),
        .mem_ready_o (mem_ready)
    );

    // geacao de clock (periodo: 10ns)
    always #5 clk = ~clk;

    // 3 rotina principal de testes
    // ---- PARA FACILITAR OS TESTES ----
    // essas funções evitam  repitir as mesmas 10 linhas de codigo para cada leitura/escrita
    task automatic do_read(input logic [31:0] addr);
        $display("[%0t] READ  -> Endereco: 0x%08h", $time, addr);
        cpu_req = 1;
        cpu_write = 0;
        cpu_addr = addr;
        wait(cpu_ready == 1); // Fica travado aqui até a cache avisar que terminou
        @(posedge clk);
        cpu_req = 0;
        #10;
    endtask

    task automatic do_write(input logic [31:0] addr, input logic [31:0] data);
        $display("[%0t] WRITE -> Endereco: 0x%08h | Dado: 0x%08h", $time, addr, data);
        cpu_req = 1;
        cpu_write = 1;
        cpu_addr = addr;
        cpu_wdata = data;
        wait(cpu_ready == 1);
        @(posedge clk);
        cpu_req = 0;
        cpu_write = 0;
        #10;
    endtask

    // ---- ROTINA PRINCIPAL DE TESTES ----
    initial begin
        // arquivo para o GTKWave
        $dumpfile("dump.vcd");
        $dumpvars(0, tb_cache);

        // 1 inicializacao (estado vazio) 
        clk = 0;
        rst_n = 0;
        cpu_req = 0;
        cpu_addr = 0;
        cpu_write = 0;
        cpu_wdata = 0;

        #15 rst_n = 1;
        #10;

        $display("\n--- INICIANDO BATERIA DE TESTES ---");

        // ========================================================= //
        // 7.1 testes de leitura (read path)
        // ========================================================= //
        $display("\n[TESTE 7.1] Leitura - Miss seguido de Hit");
        do_read(32'h00000000);  // MISS: busca o bloco 0 na memória
        do_read(32'h00000000);  // HIT: ta na cache

        // ========================================================= //
        // 7.2 teste de escrita (write path)
        // ========================================================= //
        $display("\n[TESTE 7.2] Escrita - Hit (Write-Through) e Miss (No-Write-Allocate)");
        // escreve em um endereço que já está na cache (Hit)
        do_write(32'h00000004, 32'h00000207); 
        
        // escreve em um bloco que NÃO está na cache (Miss)
        // pela nossa implementacao, vai direto para a mem e não traz o bloco
        do_write(32'h00000040, 32'h000000F1); 

        // ========================================================= //
        // 7.3 e 7.4 testes de substituição e consistência (conflito de indice)
        // ========================================================= //
        $display("\n[TESTE 7.3 e 7.4] Conflito de Mapeamento (Substituicao de Bloco)");
        // enderecos 0x00000010 e 0x00000410 mapeiam para o MESMO índice (linha 1 da cache)
        // mas possuem tags diferentes, acessar em sequência força a expulsão do bloco
        do_read(32'h00000010);  // MISS: carrega tag 0 na linha 1
        do_read(32'h00000410);  // MISS: expulsa tag 0 e carrega tag 1 na linha 1
        do_read(32'h00000010);  // MISS: expulsa tag 1 e carrega tag 0 dnv (evidência do conflito)

        // ========================================================= //
        // 7.5 testes de casos limite
        // ========================================================= //
        $display("\n[TESTE 7.5] Acesso a Endereco Extremo");
        // endereço na ultima posição possível de 32 bits (alinhado a palavra)
        do_read(32'hFFFFFFF0);

        $display("\n--- SIMULACAO CONCLUIDA COM SUCESSO ---");
        $finish;
    end

endmodule

output/dump.vcd
$date
	Tue May 26 19:05:19 2026
$end
$version
	Icarus Verilog
$end
$timescale
	1ps
$end
$scope module tb_cache $end
$var wire 1 ! mem_write $end
$var wire 128 " mem_wdata [127:0] $end
$var wire 1 # mem_req $end
$var wire 1 $ mem_ready $end
$var wire 128 % mem_rdata [127:0] $end
$var wire 32 & mem_addr [31:0] $end
$var wire 1 ' cpu_ready $end
$var wire 32 ( cpu_rdata [31:0] $end
$var reg 1 ) clk $end
$var reg 32 * cpu_addr [31:0] $end
$var reg 1 + cpu_req $end
$var reg 32 , cpu_wdata [31:0] $end
$var reg 1 - cpu_write $end
$var reg 1 . rst_n $end
$scope module u_cache $end
$var wire 1 / cache_hit $end
$var wire 1 ) clk $end
$var wire 32 0 cpu_addr_i [31:0] $end
$var wire 1 + cpu_req_i $end
$var wire 32 1 cpu_wdata_i [31:0] $end
$var wire 1 - cpu_write_i $end
$var wire 1 . rst_n $end
$var wire 2 2 word_offset [1:0] $end
$var wire 1 3 valid_from_cache $end
$var wire 22 4 tag_from_cache [21:0] $end
$var wire 1 $ mem_ready_i $end
$var wire 128 5 mem_rdata_i [127:0] $end
$var wire 128 6 data_from_cache [127:0] $end
$var wire 22 7 cpu_tag [21:0] $end
$var wire 32 8 cpu_rdata_o [31:0] $end
$var wire 6 9 cpu_index [5:0] $end
$var reg 1 ' cpu_ready_o $end
$var reg 2 : current_state [1:0] $end
$var reg 128 ; data_to_cache [127:0] $end
$var reg 1 < data_we $end
$var reg 2 = data_word_mask [1:0] $end
$var reg 32 > mem_addr_o [31:0] $end
$var reg 1 # mem_req_o $end
$var reg 128 ? mem_wdata_o [127:0] $end
$var reg 1 ! mem_write_o $end
$var reg 2 @ next_state [1:0] $end
$var reg 1 A tag_we $end
$scope module u_data_array $end
$var wire 1 ) clk $end
$var wire 128 B data_i [127:0] $end
$var wire 6 C index_i [5:0] $end
$var wire 1 < we_i $end
$var wire 2 D word_en_i [1:0] $end
$var wire 128 E data_o [127:0] $end
$upscope $end
$scope module u_tag_array $end
$var wire 1 ) clk $end
$var wire 6 F index_i [5:0] $end
$var wire 1 . rst_n $end
$var wire 22 G tag_i [21:0] $end
$var wire 22 H tag_o [21:0] $end
$var wire 1 3 valid_o $end
$var wire 1 A we_i $end
$var integer 32 I i [31:0] $end
$upscope $end
$upscope $end
$scope module u_mem $end
$var wire 1 ) clk $end
$var wire 32 J mem_addr_i [31:0] $end
$var wire 1 # mem_req_i $end
$var wire 128 K mem_wdata_i [127:0] $end
$var wire 1 ! mem_write_i $end
$var wire 1 . rst_n $end
$var wire 8 L block_addr [7:0] $end
$var reg 3 M delay_counter [2:0] $end
$var reg 128 N mem_rdata_o [127:0] $end
$var reg 1 $ mem_ready_o $end
$var integer 32 O i [31:0] $end
$scope begin $unm_blk_34 $end
$var reg 2 P w_offset [1:0] $end
$upscope $end
$upscope $end
$scope task do_read $end
$upscope $end
$scope task do_write $end
$upscope $end
$upscope $end
$enddefinitions $end
$comment Show the parameter values. $end
$dumpall
$end
#0
$dumpvars
bx P
b100000000 O
b0 N
b0 M
b0 L
b0 K
b0 J
b1000000 I
b0 H
b0 G
b0 F
bx E
b0 D
b0 C
b0 B
0A
b0 @
b0 ?
b0 >
b0 =
0<
b0 ;
b0 :
b0 9
bx 8
b0 7
bx 6
b0 5
b0 4
03
b0 2
b0 1
b0 0
0/
0.
0-
b0 ,
0+
b0 *
0)
bx (
0'
b0 &
b0 %
0$
0#
b0 "
0!
$end
#5000
b100000000 O
b1000000 I
1)
#10000
0)
#15000
1)
1.
#20000
0)
#25000
b1 :
b10 @
1)
1+
#30000
0)
#35000
1#
b10 :
1)
#40000
0)
#45000
b1 M
1)
#50000
0)
#55000
b10 M
1)
#60000
0)
#65000
b11 M
1)
#70000
0)
#75000
b11 @
1A
b11000000000000000000000000000000100000000000000000000000000000000100000000000000000000000000000000 ;
b11000000000000000000000000000000100000000000000000000000000000000100000000000000000000000000000000 B
1<
1#
b11000000000000000000000000000000100000000000000000000000000000000100000000000000000000000000000000 %
b11000000000000000000000000000000100000000000000000000000000000000100000000000000000000000000000000 5
b11000000000000000000000000000000100000000000000000000000000000000100000000000000000000000000000000 N
b0 M
1$
1)
#80000
0)
#85000
b0 (
b0 8
b1 @
b0 ;
b0 B
0<
0A
0#
1/
b11000000000000000000000000000000100000000000000000000000000000000100000000000000000000000000000000 6
b11000000000000000000000000000000100000000000000000000000000000000100000000000000000000000000000000 E
0$
b11 :
13
1)
#90000
0)
#95000
b0 @
1'
b1 :
1)
#100000
0)
#105000
b0 :
0'
b0 @
0+
1)
#110000
0)
#115000
1'
b1 :
b0 @
1)
1+
#120000
0)
#125000
b0 :
0'
b0 @
0+
1)
#130000
0)
#135000
b100000011100000000000000000000000000000000 "
b100000011100000000000000000000000000000000 ?
b100000011100000000000000000000000000000000 K
1!
1#
b1000000111000000000000000000000010000001110000000000000000000000100000011100000000000000000000001000000111 ;
b1000000111000000000000000000000010000001110000000000000000000000100000011100000000000000000000001000000111 B
b1 =
b1 D
1<
b1 :
b1 (
b1 8
b1 2
b1 @
b100 &
b100 >
b100 J
1)
b1000000111 ,
b1000000111 1
b100 *
b100 0
1-
1+
#140000
0)
#145000
b1000000111 (
b1000000111 8
b11000000000000000000000000000000100000000000000000000000100000011100000000000000000000000000000000 6
b11000000000000000000000000000000100000000000000000000000100000011100000000000000000000000000000000 E
b1 M
1)
#150000
0)
#155000
b10 M
1)
#160000
0)
#165000
b11 M
1)
#170000
0)
#175000
b0 @
1'
b1000000111000000000000000000000010000001110000000000000000000000100000011100000000000000000000001000000111 ;
b1000000111000000000000000000000010000001110000000000000000000000100000011100000000000000000000001000000111 B
b1 =
b1 D
1<
b100000011100000000000000000000000000000000 "
b100000011100000000000000000000000000000000 ?
b100000011100000000000000000000000000000000 K
1!
1#
b0 M
1$
b1 P
1)
#180000
0)
#185000
b0 :
0$
b0 ;
b0 B
b0 =
b0 D
0<
b0 "
b0 ?
b0 K
0!
0#
0'
b0 @
0-
0+
1)
#190000
0)
#195000
b11110001000000000000000000000000111100010000000000000000000000001111000100000000000000000000000011110001 "
b11110001000000000000000000000000111100010000000000000000000000001111000100000000000000000000000011110001 ?
b11110001000000000000000000000000111100010000000000000000000000001111000100000000000000000000000011110001 K
1!
1#
b1 :
0/
bx (
bx 8
b100 L
bx 6
bx E
03
b100 9
b100 C
b100 F
b0 2
b1 @
b1000000 &
b1000000 >
b1000000 J
1)
b11110001 ,
b11110001 1
b1000000 *
b1000000 0
1-
1+
#200000
0)
#205000
b1 M
1)
#210000
0)
#215000
b10 M
1)
#220000
0)
#225000
b11 M
1)
#230000
0)
#235000
b0 @
1'
b11110001000000000000000000000000111100010000000000000000000000001111000100000000000000000000000011110001 "
b11110001000000000000000000000000111100010000000000000000000000001111000100000000000000000000000011110001 ?
b11110001000000000000000000000000111100010000000000000000000000001111000100000000000000000000000011110001 K
1!
1#
b0 M
1$
b0 P
1)
#240000
0)
#245000
b0 :
0$
b0 "
b0 ?
b0 K
0!
0#
0'
b0 @
0-
0+
1)
#250000
0)
#255000
b1 :
b1 L
b1 9
b1 C
b1 F
b10 @
b10000 &
b10000 >
b10000 J
1)
b10000 *
b10000 0
1+
#260000
0)
#265000
1#
b10 :
1)
#270000
0)
#275000
b1 M
1)
#280000
0)
#285000
b10 M
1)
#290000
0)
#295000
b11 M
1)
#300000
0)
#305000
b11 @
1A
b10011000000000000000000000000000100100000000000000000000000000001000100000000000000000000000000010000 ;
b10011000000000000000000000000000100100000000000000000000000000001000100000000000000000000000000010000 B
1<
1#
b10011000000000000000000000000000100100000000000000000000000000001000100000000000000000000000000010000 %
b10011000000000000000000000000000100100000000000000000000000000001000100000000000000000000000000010000 5
b10011000000000000000000000000000100100000000000000000000000000001000100000000000000000000000000010000 N
b0 M
1$
1)
#310000
0)
#315000
b10000 (
b10000 8
1/
b1 @
b0 ;
b0 B
0<
0A
0#
b10011000000000000000000000000000100100000000000000000000000000001000100000000000000000000000000010000 6
b10011000000000000000000000000000100100000000000000000000000000001000100000000000000000000000000010000 E
0$
13
b11 :
1)
#320000
0)
#325000
b0 @
1'
b1 :
1)
#330000
0)
#335000
b0 :
0'
b0 @
0+
1)
#340000
0)
#345000
b1 :
0/
b1000001 L
b1 7
b1 G
b10 @
b10000010000 &
b10000010000 >
b10000010000 J
1)
b10000010000 *
b10000010000 0
1+
#350000
0)
#355000
1#
b10 :
1)
#360000
0)
#365000
b1 M
1)
#370000
0)
#375000
b10 M
1)
#380000
0)
#385000
b11 M
1)
#390000
0)
#395000
b11 @
1A
b10000010011000000000000000000000100000100100000000000000000000001000001000100000000000000000000010000010000 ;
b10000010011000000000000000000000100000100100000000000000000000001000001000100000000000000000000010000010000 B
1<
1#
b10000010011000000000000000000000100000100100000000000000000000001000001000100000000000000000000010000010000 %
b10000010011000000000000000000000100000100100000000000000000000001000001000100000000000000000000010000010000 5
b10000010011000000000000000000000100000100100000000000000000000001000001000100000000000000000000010000010000 N
b0 M
1$
1)
#400000
0)
#405000
b10000010000 (
b10000010000 8
1/
b1 @
b0 ;
b0 B
0<
0A
0#
b10000010011000000000000000000000100000100100000000000000000000001000001000100000000000000000000010000010000 6
b10000010011000000000000000000000100000100100000000000000000000001000001000100000000000000000000010000010000 E
b11 :
b1 4
b1 H
0$
1)
#410000
0)
#415000
b0 @
1'
b1 :
1)
#420000
0)
#425000
b0 :
0'
b0 @
0+
1)
#430000
0)
#435000
b1 :
0/
b1 L
b0 7
b0 G
b10 @
b10000 &
b10000 >
b10000 J
1)
b10000 *
b10000 0
1+
#440000
0)
#445000
1#
b10 :
1)
#450000
0)
#455000
b1 M
1)
#460000
0)
#465000
b10 M
1)
#470000
0)
#475000
b11 M
1)
#480000
0)
#485000
b11 @
1A
b10011000000000000000000000000000100100000000000000000000000000001000100000000000000000000000000010000 ;
b10011000000000000000000000000000100100000000000000000000000000001000100000000000000000000000000010000 B
1<
1#
b10011000000000000000000000000000100100000000000000000000000000001000100000000000000000000000000010000 %
b10011000000000000000000000000000100100000000000000000000000000001000100000000000000000000000000010000 5
b10011000000000000000000000000000100100000000000000000000000000001000100000000000000000000000000010000 N
b0 M
1$
1)
#490000
0)
#495000
b10000 (
b10000 8
1/
b1 @
b0 ;
b0 B
0<
0A
0#
b10011000000000000000000000000000100100000000000000000000000000001000100000000000000000000000000010000 6
b10011000000000000000000000000000100100000000000000000000000000001000100000000000000000000000000010000 E
0$
b0 4
b0 H
b11 :
1)
#500000
0)
#505000
b0 @
1'
b1 :
1)
#510000
0)
#515000
b0 :
0'
b0 @
0+
1)
#520000
0)
#525000
b1 :
bx (
bx 8
0/
b11111111 L
b1111111111111111111111 7
b1111111111111111111111 G
bx 6
bx E
03
b111111 9
b111111 C
b111111 F
b10 @
b11111111111111111111111111110000 &
b11111111111111111111111111110000 >
b11111111111111111111111111110000 J
1)
b11111111111111111111111111110000 *
b11111111111111111111111111110000 0
1+
#530000
0)
#535000
1#
b10 :
1)
#540000
0)
#545000
b1 M
1)
#550000
0)
#555000
b10 M
1)
#560000
0)
#565000
b11 M
1)
#570000
0)
#575000
b11 @
1A
b111111110011000000000000000000001111111100100000000000000000000011111111000100000000000000000000111111110000 ;
b111111110011000000000000000000001111111100100000000000000000000011111111000100000000000000000000111111110000 B
1<
1#
b111111110011000000000000000000001111111100100000000000000000000011111111000100000000000000000000111111110000 %
b111111110011000000000000000000001111111100100000000000000000000011111111000100000000000000000000111111110000 5
b111111110011000000000000000000001111111100100000000000000000000011111111000100000000000000000000111111110000 N
b0 M
1$
1)
#580000
0)
#585000
b111111110000 (
b111111110000 8
1/
b1 @
b0 ;
b0 B
0<
0A
0#
b111111110011000000000000000000001111111100100000000000000000000011111111000100000000000000000000111111110000 6
b111111110011000000000000000000001111111100100000000000000000000011111111000100000000000000000000111111110000 E
b11 :
b1111111111111111111111 4
b1111111111111111111111 H
13
0$
1)
#590000
0)
#595000
b0 @
1'
b1 :
1)
#600000
0)
#605000
b0 :
0'
b0 @
0+
1)
